secretsdump_ng/__init__.py
secretsdump_ng/secretsdump_ng.py
secretsdump_ng-1.1.2.dist-info/licenses/LICENSE
secretsdump_ng-1.1.2.dist-info/METADATA
secretsdump_ng-1.1.2.dist-info/WHEEL
secretsdump_ng-1.1.2.dist-info/entry_points.txt
secretsdump_ng-1.1.2.dist-info/top_level.txt
secretsdump_ng-1.1.2.dist-info/RECORD
