Metadata-Version: 2.4
Name: secretsdump-ng
Version: 1.1.2
Summary: Next-generation secretsdump tool using DSInternals for credential extraction
Author: Khael
Project-URL: Homepage, https://github.com/KhaelK138/secretsdump-ng
Project-URL: Repository, https://github.com/KhaelK138/secretsdump-ng
Project-URL: Issues, https://github.com/KhaelK138/secretsdump-ng/issues
Keywords: security,pentest,active-directory,credentials,secretsdump,secretsdump-ng
Classifier: Development Status :: 4 - Beta
Classifier: Intended Audience :: Information Technology
Classifier: Intended Audience :: System Administrators
Classifier: Programming Language :: Python :: 3
Classifier: Programming Language :: Python :: 3.8
Classifier: Programming Language :: Python :: 3.9
Classifier: Programming Language :: Python :: 3.10
Classifier: Programming Language :: Python :: 3.11
Classifier: Programming Language :: Python :: 3.12
Classifier: Topic :: Security
Requires-Python: >=3.8
License-File: LICENSE
Requires-Dist: impacket>=0.11.0
Provides-Extra: dev
Requires-Dist: build; extra == "dev"
Requires-Dist: twine; extra == "dev"
Dynamic: license-file
